{"features":[{"id":"1","geometry":{"coordinates":{"longitude":2.1870679,"altitude":"NaN","latitude":41.394581},"properties":{},"crs":null,"bbox":null},"properties":{"Desc:":"Accident in Carrer de la Marina between two trucks with hazardous material","Cod:":"1"},"crs":null,"bbox":null},{"id":"2","geometry":{"coordinates":{"longitude":2.1823428,"altitude":"NaN","latitude":41.392963},"properties":{},"crs":null,"bbox":null},"properties":{"Desc:":"Maintenance in Avinguda Vilanova","Cod:":"2"},"crs":null,"bbox":null},{"id":"3","geometry":{"coordinates":{"longitude":2.1543161946127394,"altitude":"NaN","latitude":41.38525301714738},"properties":{},"crs":null,"bbox":null},"properties":{"Desc:":"Workers strike in Avinguda de Roma","Cod:":"3"},"crs":null,"bbox":null},{"id":"4","geometry":{"coordinates":{"longitude":2.1556427,"altitude":"NaN","latitude":41.3955716},"properties":{},"crs":null,"bbox":null},"properties":{"Desc:":"Lane closures on Via Augusta","Cod:":"4"},"crs":null,"bbox":null},{"id":"8","geometry":{"coordinates":{"longitude":2.17666625976762,"altitude":"NaN","latitude":41.3958439711026},"properties":{},"crs":null,"bbox":null},"properties":{"Desc:":"Fans riot outside football stadium","Cod:":"8"},"crs":null,"bbox":null},{"id":"9","geometry":{"coordinates":{"longitude":2.16567993164262,"altitude":"NaN","latitude":41.3876019552962},"properties":{},"crs":null,"bbox":null},"properties":{"Desc:":"Remodeling wax museum","Cod:":"9"},"crs":null,"bbox":null},{"id":"10","geometry":{"coordinates":{"longitude":2.1697998046895,"altitude":"NaN","latitude":41.3948137762731},"properties":{},"crs":null,"bbox":null},"properties":{"Desc:":"Protest of activists in front of slaughterhouse","Cod:":"10"},"crs":null,"bbox":null},{"id":"11","geometry":{"coordinates":{"longitude":-6.00241328412881,"altitude":"NaN","latitude":37.3734828468476},"properties":{},"crs":null,"bbox":null},"properties":{"Desc:":"Node:pb01, Alarm Type: ALARMA 1, Flood Depth:0, Time Max. Flood: 01/10/2014 16:04:00, Event start: , Event end: ","Cod:":"NetTestNoInflowsRain_2014:09:30:13:00:59_pb01"},"crs":null,"bbox":null},{"id":"12","geometry":{"coordinates":{"longitude":-6.0009243057943,"altitude":"NaN","latitude":37.3743323003151},"properties":{},"crs":null,"bbox":null},"properties":{"Desc:":"Node:n03, Alarm Type: ALARMA 1, Flood Depth:0,29, Time Max. Flood: 01/10/2014 16:06:00, Event start: 2014:10:02:0:00:00, Event end: 2014:10:02:0:00:00","Cod:":"NetTestNoInflowsRain_2014:09:30:13:00:59_n03"},"crs":null,"bbox":null},{"id":"13","geometry":{"coordinates":{"longitude":-6.00089057549268,"altitude":"NaN","latitude":37.3735279458035},"properties":{},"crs":null,"bbox":null},"properties":{"Desc:":"Node:pb05, Alarm Type: ALARMA 2, Flood Depth:0,42, Time Max. Flood: 01/10/2014 16:06:00, Event start: 2014:10:02:0:00:00, Event end: 2014:10:02:0:00:00","Cod:":"NetTestNoInflowsRain_2014:09:30:13:00:59_pb05"},"crs":null,"bbox":null},{"id":"14","geometry":{"coordinates":{"longitude":-6.00171405340609,"altitude":"NaN","latitude":37.3745841191212},"properties":{},"crs":null,"bbox":null},"properties":{"Desc:":"Node:Nuevo2, Alarm Type: ALARMA 1, Flood Depth:0,133, Time Max. Flood: 01/10/2014 16:05:00, Event start: 2014:10:02:0:00:00, Event end: 2014:10:02:0:00:00","Cod:":"NetTestNoInflowsRain_2014:09:30:13:00:59_Nuevo2"},"crs":null,"bbox":null},{"id":"15","geometry":{"coordinates":{"longitude":-5.99520092079263,"altitude":"NaN","latitude":37.3753827747689},"properties":{},"crs":null,"bbox":null},"properties":{"Desc:":"Discharge:WR-01, Alarm Type: ALARMA 3, Total volume:679813,2, Critical Point: CPO-01, Event start: 2014:10:01:13:00:00, Event end: 2014:10:02:0:00:00","Cod:":"NetTestNoInflowsRain_2014:09:30:13:00:59_WR-01"},"crs":null,"bbox":null},{"id":"16","geometry":{"coordinates":{"longitude":-5.99329690170765,"altitude":"NaN","latitude":37.3756603322934},"properties":{},"crs":null,"bbox":null},"properties":{"Desc:":"Critical Point:CPO-01, Alarm Type: ALARMA 2, Max. Flow:129,563","Cod:":"NetTestNoInflowsRain_2014:09:30:13:00:59_CPO-01"},"crs":null,"bbox":null},{"id":"17","geometry":{"coordinates":{"longitude":-6.00241328412881,"altitude":"NaN","latitude":37.3734828468476},"properties":{},"crs":null,"bbox":null},"properties":{"Desc:":"Node:pb01, Alarm Type: ALARMA 1, Flood Depth:0, Time Max. Flood: 01/10/2014 4:04:00, Event start: , Event end: ","Cod:":"NetTestNoInflowsRain_2014:09:30:13:12:09_pb01"},"crs":null,"bbox":null},{"id":"18","geometry":{"coordinates":{"longitude":-6.0009243057943,"altitude":"NaN","latitude":37.3743323003151},"properties":{},"crs":null,"bbox":null},"properties":{"Desc:":"Node:n03, Alarm Type: ALARMA 1, Flood Depth:0,29, Time Max. Flood: 01/10/2014 4:21:00, Event start: 2014:10:01:13:00:00, Event end: 2014:10:01:13:00:00","Cod:":"NetTestNoInflowsRain_2014:09:30:13:12:09_n03"},"crs":null,"bbox":null},{"id":"19","geometry":{"coordinates":{"longitude":-6.00089057549268,"altitude":"NaN","latitude":37.3735279458035},"properties":{},"crs":null,"bbox":null},"properties":{"Desc:":"Node:pb05, Alarm Type: ALARMA 2, Flood Depth:0,42, Time Max. Flood: 01/10/2014 4:06:00, Event start: 2014:10:01:13:00:00, Event end: 2014:10:01:13:00:00","Cod:":"NetTestNoInflowsRain_2014:09:30:13:12:09_pb05"},"crs":null,"bbox":null},{"id":"20","geometry":{"coordinates":{"longitude":-6.00171405340609,"altitude":"NaN","latitude":37.3745841191212},"properties":{},"crs":null,"bbox":null},"properties":{"Desc:":"Node:Nuevo2, Alarm Type: ALARMA 1, Flood Depth:0,133, Time Max. Flood: 01/10/2014 4:05:00, Event start: 2014:10:01:13:00:00, Event end: 2014:10:01:13:00:00","Cod:":"NetTestNoInflowsRain_2014:09:30:13:12:09_Nuevo2"},"crs":null,"bbox":null},{"id":"21","geometry":{"coordinates":{"longitude":-5.99520092079263,"altitude":"NaN","latitude":37.3753827747689},"properties":{},"crs":null,"bbox":null},"properties":{"Desc:":"Discharge:WR-01, Alarm Type: ALARMA 3, Total volume:696164,4, Critical Point: CPO-01, Event start: 2014:10:01:2:00:00, Event end: 2014:10:01:13:00:00","Cod:":"NetTestNoInflowsRain_2014:09:30:13:12:09_WR-01"},"crs":null,"bbox":null},{"id":"22","geometry":{"coordinates":{"longitude":-5.99329690170765,"altitude":"NaN","latitude":37.3756603322934},"properties":{},"crs":null,"bbox":null},"properties":{"Desc:":"Critical Point:CPO-01, Alarm Type: ALARMA 2, Max. Flow:129,718","Cod:":"NetTestNoInflowsRain_2014:09:30:13:12:09_CPO-01"},"crs":null,"bbox":null},{"id":"23","geometry":{"coordinates":{"longitude":-6.00241328412881,"altitude":"NaN","latitude":37.3734828468476},"properties":{},"crs":null,"bbox":null},"properties":{"Desc:":"Node:pb01, Alarm Type: ALARMA 1, Flood Depth:0, Time Max. Flood: 01/10/2014 4:04:00, Event start: , Event end: ","Cod:":"NetTestNoInflowsRain_2014:09:30:13:12:46_pb01"},"crs":null,"bbox":null},{"id":"24","geometry":{"coordinates":{"longitude":-6.0009243057943,"altitude":"NaN","latitude":37.3743323003151},"properties":{},"crs":null,"bbox":null},"properties":{"Desc:":"Node:n03, Alarm Type: ALARMA 1, Flood Depth:0,29, Time Max. Flood: 01/10/2014 4:06:00, Event start: 2014:10:01:13:00:00, Event end: 2014:10:01:13:00:00","Cod:":"NetTestNoInflowsRain_2014:09:30:13:12:46_n03"},"crs":null,"bbox":null},{"id":"25","geometry":{"coordinates":{"longitude":-6.00089057549268,"altitude":"NaN","latitude":37.3735279458035},"properties":{},"crs":null,"bbox":null},"properties":{"Desc:":"Node:pb05, Alarm Type: ALARMA 2, Flood Depth:0,42, Time Max. Flood: 01/10/2014 4:07:00, Event start: 2014:10:01:13:00:00, Event end: 2014:10:01:13:00:00","Cod:":"NetTestNoInflowsRain_2014:09:30:13:12:46_pb05"},"crs":null,"bbox":null},{"id":"26","geometry":{"coordinates":{"longitude":-6.00171405340609,"altitude":"NaN","latitude":37.3745841191212},"properties":{},"crs":null,"bbox":null},"properties":{"Desc:":"Node:Nuevo2, Alarm Type: ALARMA 1, Flood Depth:0,123, Time Max. Flood: 01/10/2014 4:05:00, Event start: 2014:10:01:13:00:00, Event end: 2014:10:01:13:00:00","Cod:":"NetTestNoInflowsRain_2014:09:30:13:12:46_Nuevo2"},"crs":null,"bbox":null},{"id":"27","geometry":{"coordinates":{"longitude":-5.99520092079263,"altitude":"NaN","latitude":37.3753827747689},"properties":{},"crs":null,"bbox":null},"properties":{"Desc:":"Discharge:WR-01, Alarm Type: ALARMA 3, Total volume:619592,4, Critical Point: CPO-01, Event start: 2014:10:01:2:00:00, Event end: 2014:10:01:13:00:00","Cod:":"NetTestNoInflowsRain_2014:09:30:13:12:46_WR-01"},"crs":null,"bbox":null},{"id":"28","geometry":{"coordinates":{"longitude":-5.99329690170765,"altitude":"NaN","latitude":37.3756603322934},"properties":{},"crs":null,"bbox":null},"properties":{"Desc:":"Critical Point:CPO-01, Alarm Type: ALARMA 2, Max. Flow:138,121","Cod:":"NetTestNoInflowsRain_2014:09:30:13:12:46_CPO-01"},"crs":null,"bbox":null},{"id":"29","geometry":{"coordinates":{"longitude":-6.0009243057943,"altitude":"NaN","latitude":37.3743323003151},"properties":{},"crs":null,"bbox":null},"properties":{"Desc:":"Node:n03, Alarm Type: ALARMA 1, Flood Depth:0,29, Time Max. Flood: 02/10/2014 3:06:00, Event start: 2014:10:02:12:00:00, Event end: 2014:10:02:12:00:00","Cod:":"NetTestNoInflowsRain_2014:09:30:13:16:07_n03"},"crs":null,"bbox":null},{"id":"30","geometry":{"coordinates":{"longitude":-6.00089057549268,"altitude":"NaN","latitude":37.3735279458035},"properties":{},"crs":null,"bbox":null},"properties":{"Desc:":"Node:pb05, Alarm Type: ALARMA 2, Flood Depth:0,42, Time Max. Flood: 02/10/2014 3:06:00, Event start: 2014:10:02:12:00:00, Event end: 2014:10:02:12:00:00","Cod:":"NetTestNoInflowsRain_2014:09:30:13:16:07_pb05"},"crs":null,"bbox":null},{"id":"31","geometry":{"coordinates":{"longitude":-6.00171405340609,"altitude":"NaN","latitude":37.3745841191212},"properties":{},"crs":null,"bbox":null},"properties":{"Desc:":"Node:Nuevo2, Alarm Type: ALARMA 1, Flood Depth:0,133, Time Max. Flood: 02/10/2014 3:05:00, Event start: 2014:10:02:12:00:00, Event end: 2014:10:02:12:00:00","Cod:":"NetTestNoInflowsRain_2014:09:30:13:16:07_Nuevo2"},"crs":null,"bbox":null},{"id":"32","geometry":{"coordinates":{"longitude":-5.99520092079263,"altitude":"NaN","latitude":37.3753827747689},"properties":{},"crs":null,"bbox":null},"properties":{"Desc:":"Discharge:WR-01, Alarm Type: ALARMA 3, Total volume:695833,2, Critical Point: CPO-01, Event start: 2014:10:02:1:00:00, Event end: 2014:10:02:12:00:00","Cod:":"NetTestNoInflowsRain_2014:09:30:13:16:07_WR-01"},"crs":null,"bbox":null},{"id":"33","geometry":{"coordinates":{"longitude":-5.99329690170765,"altitude":"NaN","latitude":37.3756603322934},"properties":{},"crs":null,"bbox":null},"properties":{"Desc:":"Critical Point:CPO-01, Alarm Type: ALARMA 2, Max. Flow:129,62","Cod:":"NetTestNoInflowsRain_2014:09:30:13:16:07_CPO-01"},"crs":null,"bbox":null},{"id":"34","geometry":{"coordinates":{"longitude":-6.00241328412881,"altitude":"NaN","latitude":37.3734828468476},"properties":{},"crs":null,"bbox":null},"properties":{"Desc:":"Node:pb01, Alarm Type: ALARMA 1, Flood Depth:0, Time Max. Flood: 02/10/2014 3:04:00, Event start: , Event end: ","Cod:":"NetTestNoInflowsRain_2014:09:30:13:24:06_pb01"},"crs":null,"bbox":null},{"id":"35","geometry":{"coordinates":{"longitude":-6.0009243057943,"altitude":"NaN","latitude":37.3743323003151},"properties":{},"crs":null,"bbox":null},"properties":{"Desc:":"Node:n03, Alarm Type: ALARMA 1, Flood Depth:0,29, Time Max. Flood: 02/10/2014 3:06:00, Event start: 2014:10:02:12:00:00, Event end: 2014:10:02:12:00:00","Cod:":"NetTestNoInflowsRain_2014:09:30:13:24:06_n03"},"crs":null,"bbox":null},{"id":"36","geometry":{"coordinates":{"longitude":-6.00089057549268,"altitude":"NaN","latitude":37.3735279458035},"properties":{},"crs":null,"bbox":null},"properties":{"Desc:":"Node:pb05, Alarm Type: ALARMA 2, Flood Depth:0,42, Time Max. Flood: 02/10/2014 3:07:00, Event start: 2014:10:02:12:00:00, Event end: 2014:10:02:12:00:00","Cod:":"NetTestNoInflowsRain_2014:09:30:13:24:06_pb05"},"crs":null,"bbox":null},{"id":"37","geometry":{"coordinates":{"longitude":-6.00171405340609,"altitude":"NaN","latitude":37.3745841191212},"properties":{},"crs":null,"bbox":null},"properties":{"Desc:":"Node:Nuevo2, Alarm Type: ALARMA 1, Flood Depth:0,123, Time Max. Flood: 02/10/2014 3:05:00, Event start: 2014:10:02:12:00:00, Event end: 2014:10:02:12:00:00","Cod:":"NetTestNoInflowsRain_2014:09:30:13:24:06_Nuevo2"},"crs":null,"bbox":null},{"id":"38","geometry":{"coordinates":{"longitude":-5.99520092079263,"altitude":"NaN","latitude":37.3753827747689},"properties":{},"crs":null,"bbox":null},"properties":{"Desc:":"Discharge:WR-01, Alarm Type: ALARMA 3, Total volume:651934,8, Critical Point: CPO-01, Event start: 2014:10:02:1:00:00, Event end: 2014:10:02:12:00:00","Cod:":"NetTestNoInflowsRain_2014:09:30:13:24:06_WR-01"},"crs":null,"bbox":null},{"id":"39","geometry":{"coordinates":{"longitude":-5.99329690170765,"altitude":"NaN","latitude":37.3756603322934},"properties":{},"crs":null,"bbox":null},"properties":{"Desc:":"Critical Point:CPO-01, Alarm Type: ALARMA 2, Max. Flow:139,363","Cod:":"NetTestNoInflowsRain_2014:09:30:13:24:06_CPO-01"},"crs":null,"bbox":null},{"id":"40","geometry":{"coordinates":{"longitude":0.0,"altitude":"NaN","latitude":0.0},"properties":{},"crs":null,"bbox":null},"properties":{"Desc:":"SmartCity.eco event Event_1412168034273","Cod:":"evt_Event_1412168034273"},"crs":null,"bbox":null},{"id":"41","geometry":{"coordinates":{"longitude":0.0,"altitude":"NaN","latitude":0.0},"properties":{},"crs":null,"bbox":null},"properties":{"Desc:":"SmartCity.eco event Event_1412168035334","Cod:":"evt_Event_1412168035334"},"crs":null,"bbox":null},{"id":"42","geometry":{"coordinates":{"longitude":0.0,"altitude":"NaN","latitude":0.0},"properties":{},"crs":null,"bbox":null},"properties":{"Desc:":"SmartCity.eco event Event_1412168035908","Cod:":"evt_Event_1412168035908"},"crs":null,"bbox":null},{"id":"43","geometry":{"coordinates":{"longitude":0.0,"altitude":"NaN","latitude":0.0},"properties":{},"crs":null,"bbox":null},"properties":{"Desc:":"SmartCity.eco event Event_1412168036761","Cod:":"evt_Event_1412168036761"},"crs":null,"bbox":null},{"id":"44","geometry":{"coordinates":{"longitude":0.0,"altitude":"NaN","latitude":0.0},"properties":{},"crs":null,"bbox":null},"properties":{"Desc:":"SmartCity.eco event Event_1412168037245","Cod:":"evt_Event_1412168037245"},"crs":null,"bbox":null},{"id":"45","geometry":{"coordinates":{"longitude":0.0,"altitude":"NaN","latitude":0.0},"properties":{},"crs":null,"bbox":null},"properties":{"Desc:":"SmartCity.eco event Event_1412231177528","Cod:":"evt_Event_1412231177528"},"crs":null,"bbox":null},{"id":"46","geometry":{"coordinates":{"longitude":0.0,"altitude":"NaN","latitude":0.0},"properties":{},"crs":null,"bbox":null},"properties":{"Desc:":"SmartCity.eco event Event_1412231178707","Cod:":"evt_Event_1412231178707"},"crs":null,"bbox":null},{"id":"47","geometry":{"coordinates":{"longitude":0.0,"altitude":"NaN","latitude":0.0},"properties":{},"crs":null,"bbox":null},"properties":{"Desc:":"SmartCity.eco event Event_1412231179491","Cod:":"evt_Event_1412231179491"},"crs":null,"bbox":null},{"id":"48","geometry":{"coordinates":{"longitude":0.0,"altitude":"NaN","latitude":0.0},"properties":{},"crs":null,"bbox":null},"properties":{"Desc:":"SmartCity.eco event Event_1412231180104","Cod:":"evt_Event_1412231180104"},"crs":null,"bbox":null},{"id":"49","geometry":{"coordinates":{"longitude":0.0,"altitude":"NaN","latitude":0.0},"properties":{},"crs":null,"bbox":null},"properties":{"Desc:":"SmartCity.eco event Event_1412231180622","Cod:":"evt_Event_1412231180622"},"crs":null,"bbox":null},{"id":"50","geometry":{"coordinates":{"longitude":0.0,"altitude":"NaN","latitude":0.0},"properties":{},"crs":null,"bbox":null},"properties":{"Desc:":"SmartCity.eco event Event_1412237478915","Cod:":"evt_Event_1412237478915"},"crs":null,"bbox":null},{"id":"51","geometry":{"coordinates":{"longitude":0.0,"altitude":"NaN","latitude":0.0},"properties":{},"crs":null,"bbox":null},"properties":{"Desc:":"SmartCity.eco event Event_1412237479839","Cod:":"evt_Event_1412237479839"},"crs":null,"bbox":null},{"id":"52","geometry":{"coordinates":{"longitude":0.0,"altitude":"NaN","latitude":0.0},"properties":{},"crs":null,"bbox":null},"properties":{"Desc:":"SmartCity.eco event Event_1412237482201","Cod:":"evt_Event_1412237482201"},"crs":null,"bbox":null},{"id":"53","geometry":{"coordinates":{"longitude":0.0,"altitude":"NaN","latitude":0.0},"properties":{},"crs":null,"bbox":null},"properties":{"Desc:":"SmartCity.eco event Event_1412237482761","Cod:":"evt_Event_1412237482761"},"crs":null,"bbox":null},{"id":"54","geometry":{"coordinates":{"longitude":0.0,"altitude":"NaN","latitude":0.0},"properties":{},"crs":null,"bbox":null},"properties":{"Desc:":"SmartCity.eco event Event_1412237669505","Cod:":"evt_Event_1412237669505"},"crs":null,"bbox":null},{"id":"55","geometry":{"coordinates":{"longitude":0.0,"altitude":"NaN","latitude":0.0},"properties":{},"crs":null,"bbox":null},"properties":{"Desc:":"SmartCity.eco event Event_1412237670247","Cod:":"evt_Event_1412237670247"},"crs":null,"bbox":null},{"id":"56","geometry":{"coordinates":{"longitude":0.0,"altitude":"NaN","latitude":0.0},"properties":{},"crs":null,"bbox":null},"properties":{"Desc:":"SmartCity.eco event Event_1412237670853","Cod:":"evt_Event_1412237670853"},"crs":null,"bbox":null},{"id":"57","geometry":{"coordinates":{"longitude":0.0,"altitude":"NaN","latitude":0.0},"properties":{},"crs":null,"bbox":null},"properties":{"Desc:":"SmartCity.eco event Event_1412237671495","Cod:":"evt_Event_1412237671495"},"crs":null,"bbox":null},{"id":"58","geometry":{"coordinates":{"longitude":0.0,"altitude":"NaN","latitude":0.0},"properties":{},"crs":null,"bbox":null},"properties":{"Desc:":"SmartCity.eco event Event_1412237672167","Cod:":"evt_Event_1412237672167"},"crs":null,"bbox":null},{"id":"59","geometry":{"coordinates":{"longitude":0.0,"altitude":"NaN","latitude":0.0},"properties":{},"crs":null,"bbox":null},"properties":{"Desc:":"SmartCity.eco event Event_1412237672834","Cod:":"evt_Event_1412237672834"},"crs":null,"bbox":null},{"id":"60","geometry":{"coordinates":{"longitude":0.0,"altitude":"NaN","latitude":0.0},"properties":{},"crs":null,"bbox":null},"properties":{"Desc:":"SmartCity.eco event Event_1412237880816","Cod:":"evt_Event_1412237880816"},"crs":null,"bbox":null},{"id":"61","geometry":{"coordinates":{"longitude":0.0,"altitude":"NaN","latitude":0.0},"properties":{},"crs":null,"bbox":null},"properties":{"Desc:":"SmartCity.eco event Event_1412237881614","Cod:":"evt_Event_1412237881614"},"crs":null,"bbox":null},{"id":"62","geometry":{"coordinates":{"longitude":0.0,"altitude":"NaN","latitude":0.0},"properties":{},"crs":null,"bbox":null},"properties":{"Desc:":"SmartCity.eco event Event_1412237882516","Cod:":"evt_Event_1412237882516"},"crs":null,"bbox":null},{"id":"63","geometry":{"coordinates":{"longitude":0.0,"altitude":"NaN","latitude":0.0},"properties":{},"crs":null,"bbox":null},"properties":{"Desc:":"SmartCity.eco event Event_1412237883601","Cod:":"evt_Event_1412237883601"},"crs":null,"bbox":null},{"id":"64","geometry":{"coordinates":{"longitude":0.0,"altitude":"NaN","latitude":0.0},"properties":{},"crs":null,"bbox":null},"properties":{"Desc:":"SmartCity.eco event Event_1412246727766","Cod:":"evt_Event_1412246727766"},"crs":null,"bbox":null},{"id":"65","geometry":{"coordinates":{"longitude":0.0,"altitude":"NaN","latitude":0.0},"properties":{},"crs":null,"bbox":null},"properties":{"Desc:":"SmartCity.eco event Event_1412246729137","Cod:":"evt_Event_1412246729137"},"crs":null,"bbox":null},{"id":"66","geometry":{"coordinates":{"longitude":0.0,"altitude":"NaN","latitude":0.0},"properties":{},"crs":null,"bbox":null},"properties":{"Desc:":"SmartCity.eco event Event_1412246730058","Cod:":"evt_Event_1412246730058"},"crs":null,"bbox":null},{"id":"67","geometry":{"coordinates":{"longitude":0.0,"altitude":"NaN","latitude":0.0},"properties":{},"crs":null,"bbox":null},"properties":{"Desc:":"SmartCity.eco event Event_1412246731020","Cod:":"evt_Event_1412246731020"},"crs":null,"bbox":null},{"id":"68","geometry":{"coordinates":{"longitude":0.0,"altitude":"NaN","latitude":0.0},"properties":{},"crs":null,"bbox":null},"properties":{"Desc:":"SmartCity.eco event Event_1412246731847","Cod:":"evt_Event_1412246731847"},"crs":null,"bbox":null},{"id":"69","geometry":{"coordinates":{"longitude":0.0,"altitude":"NaN","latitude":0.0},"properties":{},"crs":null,"bbox":null},"properties":{"Desc:":"SmartCity.eco event Event_1412246732675","Cod:":"evt_Event_1412246732675"},"crs":null,"bbox":null},{"id":"70","geometry":{"coordinates":{"longitude":-0.5304443836212158,"altitude":"NaN","latitude":40.96764219953142},"properties":{},"crs":null,"bbox":null},"properties":{"Desc:":"Generic - Generic incident: At La plaza del pueblo (-0.530444, 40.967642)","Cod:":"70"},"crs":null,"bbox":null},{"id":"72","geometry":{"coordinates":{"longitude":0.0,"altitude":"NaN","latitude":0.0},"properties":{},"crs":null,"bbox":null},"properties":{"Desc:":"SmartCity.eco event Event_1412578221744","Cod:":"evt_Event_1412578221744"},"crs":null,"bbox":null},{"id":"73","geometry":{"coordinates":{"longitude":0.0,"altitude":"NaN","latitude":0.0},"properties":{},"crs":null,"bbox":null},"properties":{"Desc:":"SmartCity.eco event Event_1412578223172","Cod:":"evt_Event_1412578223172"},"crs":null,"bbox":null},{"id":"74","geometry":{"coordinates":{"longitude":0.0,"altitude":"NaN","latitude":0.0},"properties":{},"crs":null,"bbox":null},"properties":{"Desc:":"SmartCity.eco event Event_1412578224195","Cod:":"evt_Event_1412578224195"},"crs":null,"bbox":null},{"id":"75","geometry":{"coordinates":{"longitude":0.0,"altitude":"NaN","latitude":0.0},"properties":{},"crs":null,"bbox":null},"properties":{"Desc:":"SmartCity.eco event Event_1412578225180","Cod:":"evt_Event_1412578225180"},"crs":null,"bbox":null},{"id":"76","geometry":{"coordinates":{"longitude":0.0,"altitude":"NaN","latitude":0.0},"properties":{},"crs":null,"bbox":null},"properties":{"Desc:":"SmartCity.eco event Event_1412578226160","Cod:":"evt_Event_1412578226160"},"crs":null,"bbox":null},{"id":"77","geometry":{"coordinates":{"longitude":0.0,"altitude":"NaN","latitude":0.0},"properties":{},"crs":null,"bbox":null},"properties":{"Desc:":"SmartCity.eco event Event_1412578430023","Cod:":"evt_Event_1412578430023"},"crs":null,"bbox":null},{"id":"78","geometry":{"coordinates":{"longitude":0.0,"altitude":"NaN","latitude":0.0},"properties":{},"crs":null,"bbox":null},"properties":{"Desc:":"SmartCity.eco event Event_1412578430903","Cod:":"evt_Event_1412578430903"},"crs":null,"bbox":null},{"id":"79","geometry":{"coordinates":{"longitude":0.0,"altitude":"NaN","latitude":0.0},"properties":{},"crs":null,"bbox":null},"properties":{"Desc:":"SmartCity.eco event Event_1412578431837","Cod:":"evt_Event_1412578431837"},"crs":null,"bbox":null},{"id":"80","geometry":{"coordinates":{"longitude":0.0,"altitude":"NaN","latitude":0.0},"properties":{},"crs":null,"bbox":null},"properties":{"Desc:":"SmartCity.eco event Event_1412578432871","Cod:":"evt_Event_1412578432871"},"crs":null,"bbox":null},{"id":"81","geometry":{"coordinates":{"longitude":0.0,"altitude":"NaN","latitude":0.0},"properties":{},"crs":null,"bbox":null},"properties":{"Desc:":"SmartCity.eco event Event_1412578433714","Cod:":"evt_Event_1412578433714"},"crs":null,"bbox":null},{"id":"82","geometry":{"coordinates":{"longitude":0.0,"altitude":"NaN","latitude":0.0},"properties":{},"crs":null,"bbox":null},"properties":{"Desc:":"SmartCity.eco event Event_1412663087197","Cod:":"evt_Event_1412663087197"},"crs":null,"bbox":null},{"id":"83","geometry":{"coordinates":{"longitude":0.0,"altitude":"NaN","latitude":0.0},"properties":{},"crs":null,"bbox":null},"properties":{"Desc:":"SmartCity.eco event Event_1412663090717","Cod:":"evt_Event_1412663090717"},"crs":null,"bbox":null},{"id":"84","geometry":{"coordinates":{"longitude":0.0,"altitude":"NaN","latitude":0.0},"properties":{},"crs":null,"bbox":null},"properties":{"Desc:":"SmartCity.eco event Event_1412663092224","Cod:":"evt_Event_1412663092224"},"crs":null,"bbox":null},{"id":"85","geometry":{"coordinates":{"longitude":0.0,"altitude":"NaN","latitude":0.0},"properties":{},"crs":null,"bbox":null},"properties":{"Desc:":"SmartCity.eco event Event_1412663093585","Cod:":"evt_Event_1412663093585"},"crs":null,"bbox":null},{"id":"86","geometry":{"coordinates":{"longitude":0.0,"altitude":"NaN","latitude":0.0},"properties":{},"crs":null,"bbox":null},"properties":{"Desc:":"SmartCity.eco event Event_1412675981599","Cod:":"evt_Event_1412675981599"},"crs":null,"bbox":null},{"id":"87","geometry":{"coordinates":{"longitude":0.0,"altitude":"NaN","latitude":0.0},"properties":{},"crs":null,"bbox":null},"properties":{"Desc:":"SmartCity.eco event Event_1412675982680","Cod:":"evt_Event_1412675982680"},"crs":null,"bbox":null},{"id":"88","geometry":{"coordinates":{"longitude":0.0,"altitude":"NaN","latitude":0.0},"properties":{},"crs":null,"bbox":null},"properties":{"Desc:":"SmartCity.eco event Event_1412675983797","Cod:":"evt_Event_1412675983797"},"crs":null,"bbox":null},{"id":"89","geometry":{"coordinates":{"longitude":0.0,"altitude":"NaN","latitude":0.0},"properties":{},"crs":null,"bbox":null},"properties":{"Desc:":"SmartCity.eco event Event_1412675984803","Cod:":"evt_Event_1412675984803"},"crs":null,"bbox":null},{"id":"90","geometry":{"coordinates":{"longitude":0.0,"altitude":"NaN","latitude":0.0},"properties":{},"crs":null,"bbox":null},"properties":{"Desc:":"SmartCity.eco event Event_1412675985777","Cod:":"evt_Event_1412675985777"},"crs":null,"bbox":null},{"id":"91","geometry":{"coordinates":{"longitude":0.0,"altitude":"NaN","latitude":0.0},"properties":{},"crs":null,"bbox":null},"properties":{"Desc:":"SmartCity.eco event Event_1412678611999","Cod:":"evt_Event_1412678611999"},"crs":null,"bbox":null},{"id":"92","geometry":{"coordinates":{"longitude":0.0,"altitude":"NaN","latitude":0.0},"properties":{},"crs":null,"bbox":null},"properties":{"Desc:":"SmartCity.eco event Event_1412678613166","Cod:":"evt_Event_1412678613166"},"crs":null,"bbox":null},{"id":"93","geometry":{"coordinates":{"longitude":0.0,"altitude":"NaN","latitude":0.0},"properties":{},"crs":null,"bbox":null},"properties":{"Desc:":"SmartCity.eco event Event_1412678614273","Cod:":"evt_Event_1412678614273"},"crs":null,"bbox":null},{"id":"94","geometry":{"coordinates":{"longitude":0.0,"altitude":"NaN","latitude":0.0},"properties":{},"crs":null,"bbox":null},"properties":{"Desc:":"SmartCity.eco event Event_1412678615475","Cod:":"evt_Event_1412678615475"},"crs":null,"bbox":null},{"id":"95","geometry":{"coordinates":{"longitude":0.0,"altitude":"NaN","latitude":0.0},"properties":{},"crs":null,"bbox":null},"properties":{"Desc:":"SmartCity.eco event Event_1412678616579","Cod:":"evt_Event_1412678616579"},"crs":null,"bbox":null},{"id":"96","geometry":{"coordinates":{"longitude":0.0,"altitude":"NaN","latitude":0.0},"properties":{},"crs":null,"bbox":null},"properties":{"Desc:":"SmartCity.eco event Event_1412678617706","Cod:":"evt_Event_1412678617706"},"crs":null,"bbox":null},{"id":"97","geometry":{"coordinates":{"longitude":0.0,"altitude":"NaN","latitude":0.0},"properties":{},"crs":null,"bbox":null},"properties":{"Desc:":"SmartCity.eco event Event_1412679443458","Cod:":"evt_Event_1412679443458"},"crs":null,"bbox":null},{"id":"98","geometry":{"coordinates":{"longitude":0.0,"altitude":"NaN","latitude":0.0},"properties":{},"crs":null,"bbox":null},"properties":{"Desc:":"SmartCity.eco event Event_1412679444782","Cod:":"evt_Event_1412679444782"},"crs":null,"bbox":null},{"id":"99","geometry":{"coordinates":{"longitude":0.0,"altitude":"NaN","latitude":0.0},"properties":{},"crs":null,"bbox":null},"properties":{"Desc:":"SmartCity.eco event Event_1412679446020","Cod:":"evt_Event_1412679446020"},"crs":null,"bbox":null},{"id":"100","geometry":{"coordinates":{"longitude":0.0,"altitude":"NaN","latitude":0.0},"properties":{},"crs":null,"bbox":null},"properties":{"Desc:":"SmartCity.eco event Event_1412679447291","Cod:":"evt_Event_1412679447291"},"crs":null,"bbox":null},{"id":"101","geometry":{"coordinates":{"longitude":0.0,"altitude":"NaN","latitude":0.0},"properties":{},"crs":null,"bbox":null},"properties":{"Desc:":"SmartCity.eco event Event_1412679448475","Cod:":"evt_Event_1412679448475"},"crs":null,"bbox":null},{"id":"102","geometry":{"coordinates":{"longitude":0.0,"altitude":"NaN","latitude":0.0},"properties":{},"crs":null,"bbox":null},"properties":{"Desc:":"SmartCity.eco event Event_1412679449662","Cod:":"evt_Event_1412679449662"},"crs":null,"bbox":null},{"id":"103","geometry":{"coordinates":{"longitude":0.0,"altitude":"NaN","latitude":0.0},"properties":{},"crs":null,"bbox":null},"properties":{"Desc:":"SmartCity.eco event Event_1412679574076","Cod:":"evt_Event_1412679574076"},"crs":null,"bbox":null},{"id":"104","geometry":{"coordinates":{"longitude":0.0,"altitude":"NaN","latitude":0.0},"properties":{},"crs":null,"bbox":null},"properties":{"Desc:":"SmartCity.eco event Event_1412679575499","Cod:":"evt_Event_1412679575499"},"crs":null,"bbox":null},{"id":"105","geometry":{"coordinates":{"longitude":0.0,"altitude":"NaN","latitude":0.0},"properties":{},"crs":null,"bbox":null},"properties":{"Desc:":"SmartCity.eco event Event_1412679576940","Cod:":"evt_Event_1412679576940"},"crs":null,"bbox":null},{"id":"106","geometry":{"coordinates":{"longitude":0.0,"altitude":"NaN","latitude":0.0},"properties":{},"crs":null,"bbox":null},"properties":{"Desc:":"SmartCity.eco event Event_1412679578212","Cod:":"evt_Event_1412679578212"},"crs":null,"bbox":null},{"id":"107","geometry":{"coordinates":{"longitude":0.0,"altitude":"NaN","latitude":0.0},"properties":{},"crs":null,"bbox":null},"properties":{"Desc:":"SmartCity.eco event Event_1412679579681","Cod:":"evt_Event_1412679579681"},"crs":null,"bbox":null},{"id":"108","geometry":{"coordinates":{"longitude":0.0,"altitude":"NaN","latitude":0.0},"properties":{},"crs":null,"bbox":null},"properties":{"Desc:":"SmartCity.eco event Event_1412679713306","Cod:":"evt_Event_1412679713306"},"crs":null,"bbox":null},{"id":"109","geometry":{"coordinates":{"longitude":0.0,"altitude":"NaN","latitude":0.0},"properties":{},"crs":null,"bbox":null},"properties":{"Desc:":"SmartCity.eco event Event_1412679714719","Cod:":"evt_Event_1412679714719"},"crs":null,"bbox":null},{"id":"110","geometry":{"coordinates":{"longitude":0.0,"altitude":"NaN","latitude":0.0},"properties":{},"crs":null,"bbox":null},"properties":{"Desc:":"SmartCity.eco event Event_1412679716148","Cod:":"evt_Event_1412679716148"},"crs":null,"bbox":null},{"id":"111","geometry":{"coordinates":{"longitude":0.0,"altitude":"NaN","latitude":0.0},"properties":{},"crs":null,"bbox":null},"properties":{"Desc:":"SmartCity.eco event Event_1412679717494","Cod:":"evt_Event_1412679717494"},"crs":null,"bbox":null},{"id":"112","geometry":{"coordinates":{"longitude":0.0,"altitude":"NaN","latitude":0.0},"properties":{},"crs":null,"bbox":null},"properties":{"Desc:":"SmartCity.eco event Event_1412679718834","Cod:":"evt_Event_1412679718834"},"crs":null,"bbox":null},{"id":"113","geometry":{"coordinates":{"longitude":0.0,"altitude":"NaN","latitude":0.0},"properties":{},"crs":null,"bbox":null},"properties":{"Desc:":"SmartCity.eco event Event_1412679720220","Cod:":"evt_Event_1412679720220"},"crs":null,"bbox":null},{"id":"114","geometry":{"coordinates":{"longitude":0.0,"altitude":"NaN","latitude":0.0},"properties":{},"crs":null,"bbox":null},"properties":{"Desc:":"SmartCity.eco event Event_1412754268863","Cod:":"evt_Event_1412754268863"},"crs":null,"bbox":null},{"id":"115","geometry":{"coordinates":{"longitude":0.0,"altitude":"NaN","latitude":0.0},"properties":{},"crs":null,"bbox":null},"properties":{"Desc:":"SmartCity.eco event Event_1412754273586","Cod:":"evt_Event_1412754273586"},"crs":null,"bbox":null},{"id":"116","geometry":{"coordinates":{"longitude":0.0,"altitude":"NaN","latitude":0.0},"properties":{},"crs":null,"bbox":null},"properties":{"Desc:":"SmartCity.eco event Event_1412754276199","Cod:":"evt_Event_1412754276199"},"crs":null,"bbox":null},{"id":"117","geometry":{"coordinates":{"longitude":0.0,"altitude":"NaN","latitude":0.0},"properties":{},"crs":null,"bbox":null},"properties":{"Desc:":"SmartCity.eco event Event_1412754277937","Cod:":"evt_Event_1412754277937"},"crs":null,"bbox":null},{"id":"118","geometry":{"coordinates":{"longitude":0.0,"altitude":"NaN","latitude":0.0},"properties":{},"crs":null,"bbox":null},"properties":{"Desc:":"SmartCity.eco event Event_1412754279623","Cod:":"evt_Event_1412754279623"},"crs":null,"bbox":null},{"id":"119","geometry":{"coordinates":{"longitude":0.0,"altitude":"NaN","latitude":0.0},"properties":{},"crs":null,"bbox":null},"properties":{"Desc:":"SmartCity.eco event Event_1412762810749","Cod:":"evt_Event_1412762810749"},"crs":null,"bbox":null},{"id":"120","geometry":{"coordinates":{"longitude":0.0,"altitude":"NaN","latitude":0.0},"properties":{},"crs":null,"bbox":null},"properties":{"Desc:":"SmartCity.eco event Event_1412763556878","Cod:":"evt_Event_1412763556878"},"crs":null,"bbox":null},{"id":"121","geometry":{"coordinates":{"longitude":0.0,"altitude":"NaN","latitude":0.0},"properties":{},"crs":null,"bbox":null},"properties":{"Desc:":"SmartCity.eco event Event_1412763559547","Cod:":"evt_Event_1412763559547"},"crs":null,"bbox":null},{"id":"122","geometry":{"coordinates":{"longitude":0.0,"altitude":"NaN","latitude":0.0},"properties":{},"crs":null,"bbox":null},"properties":{"Desc:":"SmartCity.eco event Event_1412763561300","Cod:":"evt_Event_1412763561300"},"crs":null,"bbox":null},{"id":"123","geometry":{"coordinates":{"longitude":0.0,"altitude":"NaN","latitude":0.0},"properties":{},"crs":null,"bbox":null},"properties":{"Desc:":"SmartCity.eco event Event_1412763562944","Cod:":"evt_Event_1412763562944"},"crs":null,"bbox":null},{"id":"124","geometry":{"coordinates":{"longitude":0.0,"altitude":"NaN","latitude":0.0},"properties":{},"crs":null,"bbox":null},"properties":{"Desc:":"SmartCity.eco event Event_1412763564890","Cod:":"evt_Event_1412763564890"},"crs":null,"bbox":null},{"id":"125","geometry":{"coordinates":{"longitude":0.0,"altitude":"NaN","latitude":0.0},"properties":{},"crs":null,"bbox":null},"properties":{"Desc:":"SmartCity.eco event Event_1412763566711","Cod:":"evt_Event_1412763566711"},"crs":null,"bbox":null},{"id":"126","geometry":{"coordinates":{"longitude":0.0,"altitude":"NaN","latitude":0.0},"properties":{},"crs":null,"bbox":null},"properties":{"Desc:":"SmartCity.eco event Event_1412764285535","Cod:":"evt_Event_1412764285535"},"crs":null,"bbox":null},{"id":"127","geometry":{"coordinates":{"longitude":0.0,"altitude":"NaN","latitude":0.0},"properties":{},"crs":null,"bbox":null},"properties":{"Desc:":"SmartCity.eco event Event_1412764287267","Cod:":"evt_Event_1412764287267"},"crs":null,"bbox":null},{"id":"128","geometry":{"coordinates":{"longitude":0.0,"altitude":"NaN","latitude":0.0},"properties":{},"crs":null,"bbox":null},"properties":{"Desc:":"SmartCity.eco event Event_1412764288980","Cod:":"evt_Event_1412764288980"},"crs":null,"bbox":null},{"id":"129","geometry":{"coordinates":{"longitude":0.0,"altitude":"NaN","latitude":0.0},"properties":{},"crs":null,"bbox":null},"properties":{"Desc:":"SmartCity.eco event Event_1412764290703","Cod:":"evt_Event_1412764290703"},"crs":null,"bbox":null},{"id":"130","geometry":{"coordinates":{"longitude":0.0,"altitude":"NaN","latitude":0.0},"properties":{},"crs":null,"bbox":null},"properties":{"Desc:":"SmartCity.eco event Event_1412764292542","Cod:":"evt_Event_1412764292542"},"crs":null,"bbox":null},{"id":"131","geometry":{"coordinates":{"longitude":0.0,"altitude":"NaN","latitude":0.0},"properties":{},"crs":null,"bbox":null},"properties":{"Desc:":"SmartCity.eco event Event_1412764294243","Cod:":"evt_Event_1412764294243"},"crs":null,"bbox":null},{"id":"132","geometry":{"coordinates":{"longitude":0.0,"altitude":"NaN","latitude":0.0},"properties":{},"crs":null,"bbox":null},"properties":{"Desc:":"SmartCity.eco event Event_1412764295939","Cod:":"evt_Event_1412764295939"},"crs":null,"bbox":null},{"id":"133","geometry":{"coordinates":{"longitude":0.0,"altitude":"NaN","latitude":0.0},"properties":{},"crs":null,"bbox":null},"properties":{"Desc:":"SmartCity.eco event Event_1412764297689","Cod:":"evt_Event_1412764297689"},"crs":null,"bbox":null},{"id":"134","geometry":{"coordinates":{"longitude":0.0,"altitude":"NaN","latitude":0.0},"properties":{},"crs":null,"bbox":null},"properties":{"Desc:":"SmartCity.eco event Event_1412764299467","Cod:":"evt_Event_1412764299467"},"crs":null,"bbox":null},{"id":"135","geometry":{"coordinates":{"longitude":0.0,"altitude":"NaN","latitude":0.0},"properties":{},"crs":null,"bbox":null},"properties":{"Desc:":"SmartCity.eco event Event_1412767313253","Cod:":"evt_Event_1412767313253"},"crs":null,"bbox":null},{"id":"136","geometry":{"coordinates":{"longitude":0.0,"altitude":"NaN","latitude":0.0},"properties":{},"crs":null,"bbox":null},"properties":{"Desc:":"SmartCity.eco event Event_1412767315077","Cod:":"evt_Event_1412767315077"},"crs":null,"bbox":null},{"id":"137","geometry":{"coordinates":{"longitude":0.0,"altitude":"NaN","latitude":0.0},"properties":{},"crs":null,"bbox":null},"properties":{"Desc:":"SmartCity.eco event Event_1412767316670","Cod:":"evt_Event_1412767316670"},"crs":null,"bbox":null},{"id":"138","geometry":{"coordinates":{"longitude":0.0,"altitude":"NaN","latitude":0.0},"properties":{},"crs":null,"bbox":null},"properties":{"Desc:":"SmartCity.eco event Event_1412767318266","Cod:":"evt_Event_1412767318266"},"crs":null,"bbox":null},{"id":"139","geometry":{"coordinates":{"longitude":0.0,"altitude":"NaN","latitude":0.0},"properties":{},"crs":null,"bbox":null},"properties":{"Desc:":"SmartCity.eco event Event_1412767319852","Cod:":"evt_Event_1412767319852"},"crs":null,"bbox":null},{"id":"140","geometry":{"coordinates":{"longitude":-6.0009243057943,"altitude":"NaN","latitude":37.3743323003151},"properties":{},"crs":null,"bbox":null},"properties":{"Desc:":"Node:n03, Alarm Type: ALARMA 1, Flood Depth:0,29, Time Max. Flood: 10/10/2014 2:06:00, Event start: 2014:10:10:11:00:00, Event end: 2014:10:10:11:00:00","Cod:":"NetTestNoInflowsRain_2014:10:08:13:32:38_n03"},"crs":null,"bbox":null},{"id":"141","geometry":{"coordinates":{"longitude":-6.00089057549268,"altitude":"NaN","latitude":37.3735279458035},"properties":{},"crs":null,"bbox":null},"properties":{"Desc:":"Node:pb05, Alarm Type: ALARMA 2, Flood Depth:0,42, Time Max. Flood: 10/10/2014 2:07:00, Event start: 2014:10:10:11:00:00, Event end: 2014:10:10:11:00:00","Cod:":"NetTestNoInflowsRain_2014:10:08:13:32:38_pb05"},"crs":null,"bbox":null},{"id":"142","geometry":{"coordinates":{"longitude":-6.00171405340609,"altitude":"NaN","latitude":37.3745841191212},"properties":{},"crs":null,"bbox":null},"properties":{"Desc:":"Node:Nuevo2, Alarm Type: ALARMA 1, Flood Depth:0,123, Time Max. Flood: 10/10/2014 2:05:00, Event start: 2014:10:10:11:00:00, Event end: 2014:10:10:11:00:00","Cod:":"NetTestNoInflowsRain_2014:10:08:13:32:38_Nuevo2"},"crs":null,"bbox":null},{"id":"143","geometry":{"coordinates":{"longitude":-5.99520092079263,"altitude":"NaN","latitude":37.3753827747689},"properties":{},"crs":null,"bbox":null},"properties":{"Desc:":"Discharge:WR-01, Alarm Type: ALARMA 3, Total volume:631573,2, Critical Point: CPO-01, Event start: 2014:10:10:0:00:00, Event end: 2014:10:10:11:00:00","Cod:":"NetTestNoInflowsRain_2014:10:08:13:32:38_WR-01"},"crs":null,"bbox":null},{"id":"144","geometry":{"coordinates":{"longitude":-5.99329690170765,"altitude":"NaN","latitude":37.3756603322934},"properties":{},"crs":null,"bbox":null},"properties":{"Desc:":"Critical Point:CPO-01, Alarm Type: ALARMA 2, Max. Flow:134,231","Cod:":"NetTestNoInflowsRain_2014:10:08:13:32:38_CPO-01"},"crs":null,"bbox":null},{"id":"145","geometry":{"coordinates":{"longitude":-6.0009243057943,"altitude":"NaN","latitude":37.3743323003151},"properties":{},"crs":null,"bbox":null},"properties":{"Desc:":"Node:n03, Alarm Type: ALARMA 1, Flood Depth:0,29, Time Max. Flood: 08/10/2014 15:06:00, Event start: 2014:10:09:0:00:00, Event end: 2014:10:09:0:00:00","Cod:":"NetTestNoInflowsRain_2014:10:08:13:38:41_n03"},"crs":null,"bbox":null},{"id":"146","geometry":{"coordinates":{"longitude":-6.00089057549268,"altitude":"NaN","latitude":37.3735279458035},"properties":{},"crs":null,"bbox":null},"properties":{"Desc:":"Node:pb05, Alarm Type: ALARMA 2, Flood Depth:0,42, Time Max. Flood: 08/10/2014 15:07:00, Event start: 2014:10:09:0:00:00, Event end: 2014:10:09:0:00:00","Cod:":"NetTestNoInflowsRain_2014:10:08:13:38:41_pb05"},"crs":null,"bbox":null},{"id":"147","geometry":{"coordinates":{"longitude":-6.00171405340609,"altitude":"NaN","latitude":37.3745841191212},"properties":{},"crs":null,"bbox":null},"properties":{"Desc:":"Node:Nuevo2, Alarm Type: ALARMA 1, Flood Depth:0,123, Time Max. Flood: 08/10/2014 15:05:00, Event start: 2014:10:09:0:00:00, Event end: 2014:10:09:0:00:00","Cod:":"NetTestNoInflowsRain_2014:10:08:13:38:41_Nuevo2"},"crs":null,"bbox":null},{"id":"148","geometry":{"coordinates":{"longitude":-5.99520092079263,"altitude":"NaN","latitude":37.3753827747689},"properties":{},"crs":null,"bbox":null},"properties":{"Desc:":"Discharge:WR-01, Alarm Type: ALARMA 3, Total volume:709700,4, Critical Point: CPO-01, Event start: 2014:10:08:13:00:00, Event end: 2014:10:10:21:00:00","Cod:":"NetTestNoInflowsRain_2014:10:08:13:38:41_WR-01"},"crs":null,"bbox":null},{"id":"149","geometry":{"coordinates":{"longitude":-5.99329690170765,"altitude":"NaN","latitude":37.3756603322934},"properties":{},"crs":null,"bbox":null},"properties":{"Desc:":"Critical Point:CPO-01, Alarm Type: ALARMA 2, Max. Flow:139,022","Cod:":"NetTestNoInflowsRain_2014:10:08:13:38:41_CPO-01"},"crs":null,"bbox":null},{"id":"150","geometry":{"coordinates":{"longitude":-6.00241328412881,"altitude":"NaN","latitude":37.3734828468476},"properties":{},"crs":null,"bbox":null},"properties":{"Desc:":"Node:pb01, Alarm Type: ALARMA 1, Flood Depth:0, Time Max. Flood: 08/10/2014 13:04:00, Event start: , Event end: ","Cod:":"NetTestNoInflowsRain_2014:10:08:15:37:45_pb01"},"crs":null,"bbox":null},{"id":"151","geometry":{"coordinates":{"longitude":-6.0009243057943,"altitude":"NaN","latitude":37.3743323003151},"properties":{},"crs":null,"bbox":null},"properties":{"Desc:":"Node:n03, Alarm Type: ALARMA 1, Flood Depth:0,29, Time Max. Flood: 08/10/2014 13:06:00, Event start: 2014:10:09:0:00:00, Event end: 2014:10:09:0:00:00","Cod:":"NetTestNoInflowsRain_2014:10:08:15:37:45_n03"},"crs":null,"bbox":null},{"id":"152","geometry":{"coordinates":{"longitude":-6.00089057549268,"altitude":"NaN","latitude":37.3735279458035},"properties":{},"crs":null,"bbox":null},"properties":{"Desc:":"Node:pb05, Alarm Type: ALARMA 2, Flood Depth:0,42, Time Max. Flood: 08/10/2014 13:07:00, Event start: 2014:10:09:0:00:00, Event end: 2014:10:09:0:00:00","Cod:":"NetTestNoInflowsRain_2014:10:08:15:37:45_pb05"},"crs":null,"bbox":null},{"id":"153","geometry":{"coordinates":{"longitude":-6.00171405340609,"altitude":"NaN","latitude":37.3745841191212},"properties":{},"crs":null,"bbox":null},"properties":{"Desc:":"Node:Nuevo2, Alarm Type: ALARMA 1, Flood Depth:0,123, Time Max. Flood: 08/10/2014 13:05:00, Event start: 2014:10:09:0:00:00, Event end: 2014:10:09:0:00:00","Cod:":"NetTestNoInflowsRain_2014:10:08:15:37:45_Nuevo2"},"crs":null,"bbox":null},{"id":"154","geometry":{"coordinates":{"longitude":-5.99520092079263,"altitude":"NaN","latitude":37.3753827747689},"properties":{},"crs":null,"bbox":null},"properties":{"Desc:":"Discharge:WR-01, Alarm Type: ALARMA 3, Total volume:731523,6, Critical Point: CPO-01, Event start: 2014:10:08:13:00:00, Event end: 2014:10:10:21:00:00","Cod:":"NetTestNoInflowsRain_2014:10:08:15:37:45_WR-01"},"crs":null,"bbox":null},{"id":"155","geometry":{"coordinates":{"longitude":-5.99329690170765,"altitude":"NaN","latitude":37.3756603322934},"properties":{},"crs":null,"bbox":null},"properties":{"Desc:":"Critical Point:CPO-01, Alarm Type: ALARMA 2, Max. Flow:138,923","Cod:":"NetTestNoInflowsRain_2014:10:08:15:37:45_CPO-01"},"crs":null,"bbox":null},{"id":"156","geometry":{"coordinates":{"longitude":-6.0009243057943,"altitude":"NaN","latitude":37.3743323003151},"properties":{},"crs":null,"bbox":null},"properties":{"Desc:":"Node:n03, Alarm Type: ALARMA 1, Flood Depth:0,29, Time Max. Flood: 08/10/2014 18:06:00, Event start: 2014:10:09:6:00:00, Event end: 2014:10:09:6:00:00","Cod:":"NetTestNoInflowsRain_2014:10:08:16:35:46_n03"},"crs":null,"bbox":null},{"id":"157","geometry":{"coordinates":{"longitude":-6.00089057549268,"altitude":"NaN","latitude":37.3735279458035},"properties":{},"crs":null,"bbox":null},"properties":{"Desc:":"Node:pb05, Alarm Type: ALARMA 2, Flood Depth:0,42, Time Max. Flood: 08/10/2014 18:07:00, Event start: 2014:10:09:6:00:00, Event end: 2014:10:09:6:00:00","Cod:":"NetTestNoInflowsRain_2014:10:08:16:35:46_pb05"},"crs":null,"bbox":null},{"id":"158","geometry":{"coordinates":{"longitude":-6.00171405340609,"altitude":"NaN","latitude":37.3745841191212},"properties":{},"crs":null,"bbox":null},"properties":{"Desc:":"Node:Nuevo2, Alarm Type: ALARMA 1, Flood Depth:0,123, Time Max. Flood: 08/10/2014 18:05:00, Event start: 2014:10:09:6:00:00, Event end: 2014:10:09:6:00:00","Cod:":"NetTestNoInflowsRain_2014:10:08:16:35:46_Nuevo2"},"crs":null,"bbox":null},{"id":"159","geometry":{"coordinates":{"longitude":-5.99520092079263,"altitude":"NaN","latitude":37.3753827747689},"properties":{},"crs":null,"bbox":null},"properties":{"Desc:":"Discharge:WR-01, Alarm Type: ALARMA 3, Total volume:713559,6, Critical Point: CPO-01, Event start: 2014:10:08:19:00:00, Event end: 2014:10:11:3:00:00","Cod:":"NetTestNoInflowsRain_2014:10:08:16:35:46_WR-01"},"crs":null,"bbox":null},{"id":"160","geometry":{"coordinates":{"longitude":-5.99329690170765,"altitude":"NaN","latitude":37.3756603322934},"properties":{},"crs":null,"bbox":null},"properties":{"Desc:":"Critical Point:CPO-01, Alarm Type: ALARMA 2, Max. Flow:136,095","Cod:":"NetTestNoInflowsRain_2014:10:08:16:35:46_CPO-01"},"crs":null,"bbox":null},{"id":"161","geometry":{"coordinates":{"longitude":-6.0009243057943,"altitude":"NaN","latitude":37.3743323003151},"properties":{},"crs":null,"bbox":null},"properties":{"Desc:":"Node:n03, Alarm Type: ALARMA 1, Flood Depth:0,29, Time Max. Flood: 08/10/2014 18:06:00, Event start: 2014:10:09:6:00:00, Event end: 2014:10:09:6:00:00","Cod:":"NetTestNoInflowsRain_2014:10:08:16:36:16_n03"},"crs":null,"bbox":null},{"id":"162","geometry":{"coordinates":{"longitude":-6.00089057549268,"altitude":"NaN","latitude":37.3735279458035},"properties":{},"crs":null,"bbox":null},"properties":{"Desc:":"Node:pb05, Alarm Type: ALARMA 2, Flood Depth:0,42, Time Max. Flood: 08/10/2014 18:07:00, Event start: 2014:10:09:6:00:00, Event end: 2014:10:09:6:00:00","Cod:":"NetTestNoInflowsRain_2014:10:08:16:36:16_pb05"},"crs":null,"bbox":null},{"id":"163","geometry":{"coordinates":{"longitude":-6.00171405340609,"altitude":"NaN","latitude":37.3745841191212},"properties":{},"crs":null,"bbox":null},"properties":{"Desc:":"Node:Nuevo2, Alarm Type: ALARMA 1, Flood Depth:0,123, Time Max. Flood: 08/10/2014 18:05:00, Event start: 2014:10:09:6:00:00, Event end: 2014:10:09:6:00:00","Cod:":"NetTestNoInflowsRain_2014:10:08:16:36:16_Nuevo2"},"crs":null,"bbox":null},{"id":"164","geometry":{"coordinates":{"longitude":-5.99520092079263,"altitude":"NaN","latitude":37.3753827747689},"properties":{},"crs":null,"bbox":null},"properties":{"Desc:":"Discharge:WR-01, Alarm Type: ALARMA 3, Total volume:731365,2, Critical Point: CPO-01, Event start: 2014:10:08:19:00:00, Event end: 2014:10:11:3:00:00","Cod:":"NetTestNoInflowsRain_2014:10:08:16:36:16_WR-01"},"crs":null,"bbox":null},{"id":"165","geometry":{"coordinates":{"longitude":-5.99329690170765,"altitude":"NaN","latitude":37.3756603322934},"properties":{},"crs":null,"bbox":null},"properties":{"Desc:":"Critical Point:CPO-01, Alarm Type: ALARMA 2, Max. Flow:134,44","Cod:":"NetTestNoInflowsRain_2014:10:08:16:36:16_CPO-01"},"crs":null,"bbox":null},{"id":"166","geometry":{"coordinates":{"longitude":-6.00241328412881,"altitude":"NaN","latitude":37.3734828468476},"properties":{},"crs":null,"bbox":null},"properties":{"Desc:":"Node:pb01, Alarm Type: ALARMA 1, Flood Depth:0, Time Max. Flood: 10/10/2014 7:04:00, Event start: , Event end: ","Cod:":"NetTestNoInflowsRain_2014:10:08:16:44:00_pb01"},"crs":null,"bbox":null},{"id":"167","geometry":{"coordinates":{"longitude":-6.0009243057943,"altitude":"NaN","latitude":37.3743323003151},"properties":{},"crs":null,"bbox":null},"properties":{"Desc:":"Node:n03, Alarm Type: ALARMA 1, Flood Depth:0,29, Time Max. Flood: 10/10/2014 7:06:00, Event start: 2014:10:08:19:00:00, Event end: 2014:10:10:19:00:00","Cod:":"NetTestNoInflowsRain_2014:10:08:16:44:00_n03"},"crs":null,"bbox":null},{"id":"168","geometry":{"coordinates":{"longitude":-6.00089057549268,"altitude":"NaN","latitude":37.3735279458035},"properties":{},"crs":null,"bbox":null},"properties":{"Desc:":"Node:pb05, Alarm Type: ALARMA 2, Flood Depth:0,42, Time Max. Flood: 10/10/2014 7:07:00, Event start: 2014:10:08:19:00:00, Event end: 2014:10:10:19:00:00","Cod:":"NetTestNoInflowsRain_2014:10:08:16:44:00_pb05"},"crs":null,"bbox":null},{"id":"169","geometry":{"coordinates":{"longitude":-6.00171405340609,"altitude":"NaN","latitude":37.3745841191212},"properties":{},"crs":null,"bbox":null},"properties":{"Desc:":"Node:Nuevo2, Alarm Type: ALARMA 1, Flood Depth:0,123, Time Max. Flood: 10/10/2014 7:05:00, Event start: 2014:10:08:19:00:00, Event end: 2014:10:10:19:00:00","Cod:":"NetTestNoInflowsRain_2014:10:08:16:44:00_Nuevo2"},"crs":null,"bbox":null},{"id":"170","geometry":{"coordinates":{"longitude":-5.99520092079263,"altitude":"NaN","latitude":37.3753827747689},"properties":{},"crs":null,"bbox":null},"properties":{"Desc:":"Discharge:WR-01, Alarm Type: ALARMA 3, Total volume:1056268,8, Critical Point: CPO-01, Event start: 2014:10:08:19:00:00, Event end: 2014:10:10:19:00:00","Cod:":"NetTestNoInflowsRain_2014:10:08:16:44:00_WR-01"},"crs":null,"bbox":null},{"id":"171","geometry":{"coordinates":{"longitude":-5.99329690170765,"altitude":"NaN","latitude":37.3756603322934},"properties":{},"crs":null,"bbox":null},"properties":{"Desc:":"Critical Point:CPO-01, Alarm Type: ALARMA 2, Max. Flow:134,477","Cod:":"NetTestNoInflowsRain_2014:10:08:16:44:00_CPO-01"},"crs":null,"bbox":null},{"id":"172","geometry":{"coordinates":{"longitude":-6.00241328412881,"altitude":"NaN","latitude":37.3734828468476},"properties":{},"crs":null,"bbox":null},"properties":{"Desc:":"Node:pb01, Alarm Type: ALARMA 1, Flood Depth:0, Time Max. Flood: 10/10/2014 8:04:00, Event start: , Event end: ","Cod:":"NetTestNoInflowsRain_2014:10:09:9:14:45_pb01"},"crs":null,"bbox":null},{"id":"173","geometry":{"coordinates":{"longitude":-6.0009243057943,"altitude":"NaN","latitude":37.3743323003151},"properties":{},"crs":null,"bbox":null},"properties":{"Desc:":"Node:n03, Alarm Type: ALARMA 1, Flood Depth:0,29, Time Max. Flood: 10/10/2014 8:06:00, Event start: 2014:10:10:13:00:00, Event end: 2014:10:10:13:00:00","Cod:":"NetTestNoInflowsRain_2014:10:09:9:14:45_n03"},"crs":null,"bbox":null},{"id":"174","geometry":{"coordinates":{"longitude":-6.00089057549268,"altitude":"NaN","latitude":37.3735279458035},"properties":{},"crs":null,"bbox":null},"properties":{"Desc:":"Node:pb05, Alarm Type: ALARMA 2, Flood Depth:0,42, Time Max. Flood: 10/10/2014 8:07:00, Event start: 2014:10:10:13:00:00, Event end: 2014:10:10:13:00:00","Cod:":"NetTestNoInflowsRain_2014:10:09:9:14:45_pb05"},"crs":null,"bbox":null},{"id":"175","geometry":{"coordinates":{"longitude":-6.00171405340609,"altitude":"NaN","latitude":37.3745841191212},"properties":{},"crs":null,"bbox":null},"properties":{"Desc:":"Node:Nuevo2, Alarm Type: ALARMA 1, Flood Depth:0,123, Time Max. Flood: 10/10/2014 8:05:00, Event start: 2014:10:10:13:00:00, Event end: 2014:10:10:13:00:00","Cod:":"NetTestNoInflowsRain_2014:10:09:9:14:45_Nuevo2"},"crs":null,"bbox":null},{"id":"176","geometry":{"coordinates":{"longitude":-5.99520092079263,"altitude":"NaN","latitude":37.3753827747689},"properties":{},"crs":null,"bbox":null},"properties":{"Desc:":"Discharge:WR-01, Alarm Type: ALARMA 3, Total volume:627253,2, Critical Point: CPO-01, Event start: 2014:10:10:2:00:00, Event end: 2014:10:10:13:00:00","Cod:":"NetTestNoInflowsRain_2014:10:09:9:14:45_WR-01"},"crs":null,"bbox":null},{"id":"177","geometry":{"coordinates":{"longitude":-5.99329690170765,"altitude":"NaN","latitude":37.3756603322934},"properties":{},"crs":null,"bbox":null},"properties":{"Desc:":"Critical Point:CPO-01, Alarm Type: ALARMA 2, Max. Flow:135,956","Cod:":"NetTestNoInflowsRain_2014:10:09:9:14:45_CPO-01"},"crs":null,"bbox":null},{"id":"178","geometry":{"coordinates":{"longitude":-6.00241328412881,"altitude":"NaN","latitude":37.3734828468476},"properties":{},"crs":null,"bbox":null},"properties":{"Desc:":"Node:pb01, Alarm Type: ALARMA 1, Flood Depth:0, Time Max. Flood: 10/10/2014 8:04:00, Event start: , Event end: ","Cod:":"NetTestNoInflowsRain_2014:10:09:9:20:20_pb01"},"crs":null,"bbox":null},{"id":"179","geometry":{"coordinates":{"longitude":-6.0009243057943,"altitude":"NaN","latitude":37.3743323003151},"properties":{},"crs":null,"bbox":null},"properties":{"Desc:":"Node:n03, Alarm Type: ALARMA 1, Flood Depth:0, Time Max. Flood: 10/10/2014 8:07:00, Event start: , Event end: ","Cod:":"NetTestNoInflowsRain_2014:10:09:9:20:20_n03"},"crs":null,"bbox":null},{"id":"180","geometry":{"coordinates":{"longitude":-5.99760322750544,"altitude":"NaN","latitude":37.3767790815564},"properties":{},"crs":null,"bbox":null},"properties":{"Desc:":"Node:pb14, Alarm Type: ALARMA 1, Flood Depth:0, Time Max. Flood: 10/10/2014 8:06:00, Event start: , Event end: ","Cod:":"NetTestNoInflowsRain_2014:10:09:9:20:20_pb14"},"crs":null,"bbox":null},{"id":"181","geometry":{"coordinates":{"longitude":-6.00171405340609,"altitude":"NaN","latitude":37.3745841191212},"properties":{},"crs":null,"bbox":null},"properties":{"Desc:":"Node:Nuevo2, Alarm Type: ALARMA 1, Flood Depth:0,003, Time Max. Flood: 10/10/2014 8:07:00, Event start: , Event end: ","Cod:":"NetTestNoInflowsRain_2014:10:09:9:20:20_Nuevo2"},"crs":null,"bbox":null},{"id":"182","geometry":{"coordinates":{"longitude":-5.99520092079263,"altitude":"NaN","latitude":37.3753827747689},"properties":{},"crs":null,"bbox":null},"properties":{"Desc:":"Discharge:WR-01, Alarm Type: ALARMA 3, Total volume:466275,6, Critical Point: CPO-01, Event start: 2014:10:10:13:00:00, Event end: 2014:10:10:13:00:00","Cod:":"NetTestNoInflowsRain_2014:10:09:9:20:20_WR-01"},"crs":null,"bbox":null},{"id":"183","geometry":{"coordinates":{"longitude":-5.99329690170765,"altitude":"NaN","latitude":37.3756603322934},"properties":{},"crs":null,"bbox":null},"properties":{"Desc:":"Critical Point:CPO-01, Alarm Type: ALARMA 2, Max. Flow:129,521","Cod:":"NetTestNoInflowsRain_2014:10:09:9:20:20_CPO-01"},"crs":null,"bbox":null},{"id":"184","geometry":{"coordinates":{"longitude":-6.00241328412881,"altitude":"NaN","latitude":37.3734828468476},"properties":{},"crs":null,"bbox":null},"properties":{"Desc:":"Node:pb01, Alarm Type: ALARMA 1, Flood Depth:0, Time Max. Flood: 10/10/2014 8:04:00, Event start: , Event end: ","Cod:":"NetTestNoInflowsRain_2014:10:09:9:39:08_pb01"},"crs":null,"bbox":null},{"id":"185","geometry":{"coordinates":{"longitude":-6.0009243057943,"altitude":"NaN","latitude":37.3743323003151},"properties":{},"crs":null,"bbox":null},"properties":{"Desc:":"Node:n03, Alarm Type: ALARMA 2, Flood Depth:0,3, Time Max. Flood: 10/10/2014 8:06:00, Event start: 2014:10:10:13:00:00, Event end: 2014:10:10:13:00:00","Cod:":"NetTestNoInflowsRain_2014:10:09:9:39:08_n03"},"crs":null,"bbox":null},{"id":"186","geometry":{"coordinates":{"longitude":-6.00089057549268,"altitude":"NaN","latitude":37.3735279458035},"properties":{},"crs":null,"bbox":null},"properties":{"Desc:":"Node:pb05, Alarm Type: ALARMA 2, Flood Depth:0,45, Time Max. Flood: 10/10/2014 8:06:00, Event start: 2014:10:10:13:00:00, Event end: 2014:10:10:13:00:00","Cod:":"NetTestNoInflowsRain_2014:10:09:9:39:08_pb05"},"crs":null,"bbox":null},{"id":"187","geometry":{"coordinates":{"longitude":-5.99760322750544,"altitude":"NaN","latitude":37.3767790815564},"properties":{},"crs":null,"bbox":null},"properties":{"Desc:":"Node:pb14, Alarm Type: ALARMA 1, Flood Depth:0, Time Max. Flood: 10/10/2014 8:04:00, Event start: , Event end: ","Cod:":"NetTestNoInflowsRain_2014:10:09:9:39:08_pb14"},"crs":null,"bbox":null},{"id":"188","geometry":{"coordinates":{"longitude":-6.00171405340609,"altitude":"NaN","latitude":37.3745841191212},"properties":{},"crs":null,"bbox":null},"properties":{"Desc:":"Node:Nuevo2, Alarm Type: ALARMA 1, Flood Depth:0,143, Time Max. Flood: 10/10/2014 8:06:00, Event start: 2014:10:10:13:00:00, Event end: 2014:10:10:13:00:00","Cod:":"NetTestNoInflowsRain_2014:10:09:9:39:08_Nuevo2"},"crs":null,"bbox":null},{"id":"189","geometry":{"coordinates":{"longitude":-5.99520092079263,"altitude":"NaN","latitude":37.3753827747689},"properties":{},"crs":null,"bbox":null},"properties":{"Desc:":"Discharge:WR-01, Alarm Type: ALARMA 3, Total volume:1145854,8, Critical Point: CPO-01, Event start: 2014:10:10:2:00:00, Event end: 2014:10:10:16:00:00","Cod:":"NetTestNoInflowsRain_2014:10:09:9:39:08_WR-01"},"crs":null,"bbox":null},{"id":"190","geometry":{"coordinates":{"longitude":-5.99329690170765,"altitude":"NaN","latitude":37.3756603322934},"properties":{},"crs":null,"bbox":null},"properties":{"Desc:":"Critical Point:CPO-01, Alarm Type: ALARMA 3, Max. Flow:155,439","Cod:":"NetTestNoInflowsRain_2014:10:09:9:39:08_CPO-01"},"crs":null,"bbox":null},{"id":"191","geometry":{"coordinates":{"longitude":-6.0009243057943,"altitude":"NaN","latitude":37.3743323003151},"properties":{},"crs":null,"bbox":null},"properties":{"Desc:":"Node:n03, Alarm Type: ALARMA 1, Flood Depth:0, Time Max. Flood: 10/10/2014 0:08:00, Event start: , Event end: ","Cod:":"NetTestNoInflowsRain_2014:10:09:13:27:24_n03"},"crs":null,"bbox":null},{"id":"192","geometry":{"coordinates":{"longitude":-5.99760322750544,"altitude":"NaN","latitude":37.3767790815564},"properties":{},"crs":null,"bbox":null},"properties":{"Desc:":"Node:pb14, Alarm Type: ALARMA 1, Flood Depth:0, Time Max. Flood: 10/10/2014 0:06:00, Event start: , Event end: ","Cod:":"NetTestNoInflowsRain_2014:10:09:13:27:24_pb14"},"crs":null,"bbox":null},{"id":"193","geometry":{"coordinates":{"longitude":-6.00171405340609,"altitude":"NaN","latitude":37.3745841191212},"properties":{},"crs":null,"bbox":null},"properties":{"Desc:":"Node:Nuevo2, Alarm Type: ALARMA 1, Flood Depth:0,003, Time Max. Flood: 10/10/2014 0:08:00, Event start: , Event end: ","Cod:":"NetTestNoInflowsRain_2014:10:09:13:27:24_Nuevo2"},"crs":null,"bbox":null},{"id":"194","geometry":{"coordinates":{"longitude":-5.99520092079263,"altitude":"NaN","latitude":37.3753827747689},"properties":{},"crs":null,"bbox":null},"properties":{"Desc:":"Discharge:WR-01, Alarm Type: ALARMA 3, Total volume:483753,6, Critical Point: CPO-01, Event start: 2014:10:10:9:00:00, Event end: 2014:10:10:9:00:00","Cod:":"NetTestNoInflowsRain_2014:10:09:13:27:24_WR-01"},"crs":null,"bbox":null},{"id":"195","geometry":{"coordinates":{"longitude":-5.99329690170765,"altitude":"NaN","latitude":37.3756603322934},"properties":{},"crs":null,"bbox":null},"properties":{"Desc:":"Critical Point:CPO-01, Alarm Type: ALARMA 2, Max. Flow:134,376","Cod:":"NetTestNoInflowsRain_2014:10:09:13:27:24_CPO-01"},"crs":null,"bbox":null},{"id":"196","geometry":{"coordinates":{"longitude":-6.0009243057943,"altitude":"NaN","latitude":37.3743323003151},"properties":{},"crs":null,"bbox":null},"properties":{"Desc:":"Node:n03, Alarm Type: ALARMA 1, Flood Depth:0,29, Time Max. Flood: 10/10/2014 20:06:00, Event start: 2014:10:11:7:00:00, Event end: 2014:10:11:7:00:00","Cod:":"NetTestNoInflowsRain_2014:10:09:15:03:26_n03"},"crs":null,"bbox":null},{"id":"197","geometry":{"coordinates":{"longitude":-6.00089057549268,"altitude":"NaN","latitude":37.3735279458035},"properties":{},"crs":null,"bbox":null},"properties":{"Desc:":"Node:pb05, Alarm Type: ALARMA 2, Flood Depth:0,42, Time Max. Flood: 10/10/2014 20:07:00, Event start: 2014:10:11:7:00:00, Event end: 2014:10:11:7:00:00","Cod:":"NetTestNoInflowsRain_2014:10:09:15:03:26_pb05"},"crs":null,"bbox":null},{"id":"198","geometry":{"coordinates":{"longitude":-6.00171405340609,"altitude":"NaN","latitude":37.3745841191212},"properties":{},"crs":null,"bbox":null},"properties":{"Desc:":"Node:Nuevo2, Alarm Type: ALARMA 1, Flood Depth:0,123, Time Max. Flood: 10/10/2014 20:05:00, Event start: 2014:10:11:7:00:00, Event end: 2014:10:11:7:00:00","Cod:":"NetTestNoInflowsRain_2014:10:09:15:03:26_Nuevo2"},"crs":null,"bbox":null},{"id":"199","geometry":{"coordinates":{"longitude":-5.99520092079263,"altitude":"NaN","latitude":37.3753827747689},"properties":{},"crs":null,"bbox":null},"properties":{"Desc:":"Discharge:WR-01, Alarm Type: ALARMA 3, Total volume:626904, Critical Point: CPO-01, Event start: 2014:10:10:20:00:00, Event end: 2014:10:11:7:00:00","Cod:":"NetTestNoInflowsRain_2014:10:09:15:03:26_WR-01"},"crs":null,"bbox":null},{"id":"200","geometry":{"coordinates":{"longitude":-5.99329690170765,"altitude":"NaN","latitude":37.3756603322934},"properties":{},"crs":null,"bbox":null},"properties":{"Desc:":"Critical Point:CPO-01, Alarm Type: ALARMA 2, Max. Flow:138,905","Cod:":"NetTestNoInflowsRain_2014:10:09:15:03:26_CPO-01"},"crs":null,"bbox":null},{"id":"201","geometry":{"coordinates":{"longitude":-6.00241328412881,"altitude":"NaN","latitude":37.3734828468476},"properties":{},"crs":null,"bbox":null},"properties":{"Desc:":"Node:pb01, Alarm Type: ALARMA 1, Flood Depth:0, Time Max. Flood: 10/10/2014 20:04:00, Event start: , Event end: ","Cod:":"NetTestNoInflowsRain_2014:10:09:15:05:12_pb01"},"crs":null,"bbox":null},{"id":"202","geometry":{"coordinates":{"longitude":-6.0009243057943,"altitude":"NaN","latitude":37.3743323003151},"properties":{},"crs":null,"bbox":null},"properties":{"Desc:":"Node:n03, Alarm Type: ALARMA 1, Flood Depth:0, Time Max. Flood: 10/10/2014 20:07:00, Event start: , Event end: ","Cod:":"NetTestNoInflowsRain_2014:10:09:15:05:12_n03"},"crs":null,"bbox":null},{"id":"203","geometry":{"coordinates":{"longitude":-5.99760322750544,"altitude":"NaN","latitude":37.3767790815564},"properties":{},"crs":null,"bbox":null},"properties":{"Desc:":"Node:pb14, Alarm Type: ALARMA 1, Flood Depth:0, Time Max. Flood: 10/10/2014 20:06:00, Event start: , Event end: ","Cod:":"NetTestNoInflowsRain_2014:10:09:15:05:12_pb14"},"crs":null,"bbox":null},{"id":"204","geometry":{"coordinates":{"longitude":-6.00171405340609,"altitude":"NaN","latitude":37.3745841191212},"properties":{},"crs":null,"bbox":null},"properties":{"Desc:":"Node:Nuevo2, Alarm Type: ALARMA 1, Flood Depth:0,003, Time Max. Flood: 10/10/2014 20:07:00, Event start: , Event end: ","Cod:":"NetTestNoInflowsRain_2014:10:09:15:05:12_Nuevo2"},"crs":null,"bbox":null},{"id":"205","geometry":{"coordinates":{"longitude":-5.99520092079263,"altitude":"NaN","latitude":37.3753827747689},"properties":{},"crs":null,"bbox":null},"properties":{"Desc:":"Discharge:WR-01, Alarm Type: ALARMA 3, Total volume:466117,2, Critical Point: CPO-01, Event start: 2014:10:11:7:00:00, Event end: 2014:10:11:7:00:00","Cod:":"NetTestNoInflowsRain_2014:10:09:15:05:12_WR-01"},"crs":null,"bbox":null},{"id":"206","geometry":{"coordinates":{"longitude":-5.99329690170765,"altitude":"NaN","latitude":37.3756603322934},"properties":{},"crs":null,"bbox":null},"properties":{"Desc:":"Critical Point:CPO-01, Alarm Type: ALARMA 2, Max. Flow:129,477","Cod:":"NetTestNoInflowsRain_2014:10:09:15:05:12_CPO-01"},"crs":null,"bbox":null},{"id":"207","geometry":{"coordinates":{"longitude":-6.0009243057943,"altitude":"NaN","latitude":37.3743323003151},"properties":{},"crs":null,"bbox":null},"properties":{"Desc:":"Node:n03, Alarm Type: ALARMA 1, Flood Depth:0, Time Max. Flood: 10/10/2014 20:07:00, Event start: , Event end: ","Cod:":"NetTestNoInflowsRain_2014:10:09:15:09:37_n03"},"crs":null,"bbox":null},{"id":"208","geometry":{"coordinates":{"longitude":-6.00089057549268,"altitude":"NaN","latitude":37.3735279458035},"properties":{},"crs":null,"bbox":null},"properties":{"Desc:":"Node:pb05, Alarm Type: ALARMA 1, Flood Depth:0, Time Max. Flood: 10/10/2014 20:04:00, Event start: , Event end: ","Cod:":"NetTestNoInflowsRain_2014:10:09:15:09:37_pb05"},"crs":null,"bbox":null},{"id":"209","geometry":{"coordinates":{"longitude":-6.00171405340609,"altitude":"NaN","latitude":37.3745841191212},"properties":{},"crs":null,"bbox":null},"properties":{"Desc:":"Node:Nuevo2, Alarm Type: ALARMA 1, Flood Depth:0,003, Time Max. Flood: 10/10/2014 20:07:00, Event start: , Event end: ","Cod:":"NetTestNoInflowsRain_2014:10:09:15:09:37_Nuevo2"},"crs":null,"bbox":null},{"id":"210","geometry":{"coordinates":{"longitude":-5.99520092079263,"altitude":"NaN","latitude":37.3753827747689},"properties":{},"crs":null,"bbox":null},"properties":{"Desc:":"Discharge:WR-01, Alarm Type: ALARMA 3, Total volume:466149,6, Critical Point: CPO-01, Event start: 2014:10:11:7:00:00, Event end: 2014:10:11:7:00:00","Cod:":"NetTestNoInflowsRain_2014:10:09:15:09:37_WR-01"},"crs":null,"bbox":null},{"id":"211","geometry":{"coordinates":{"longitude":-5.99329690170765,"altitude":"NaN","latitude":37.3756603322934},"properties":{},"crs":null,"bbox":null},"properties":{"Desc:":"Critical Point:CPO-01, Alarm Type: ALARMA 2, Max. Flow:129,486","Cod:":"NetTestNoInflowsRain_2014:10:09:15:09:37_CPO-01"},"crs":null,"bbox":null},{"id":"212","geometry":{"coordinates":{"longitude":-6.00241328412881,"altitude":"NaN","latitude":37.3734828468476},"properties":{},"crs":null,"bbox":null},"properties":{"Desc:":"Node:pb01, Alarm Type: ALARMA 1, Flood Depth:0, Time Max. Flood: 10/10/2014 20:04:00, Event start: , Event end: ","Cod:":"NetTestNoInflowsRain_2014:10:09:15:13:28_pb01"},"crs":null,"bbox":null},{"id":"213","geometry":{"coordinates":{"longitude":-6.0009243057943,"altitude":"NaN","latitude":37.3743323003151},"properties":{},"crs":null,"bbox":null},"properties":{"Desc:":"Node:n03, Alarm Type: ALARMA 1, Flood Depth:0,29, Time Max. Flood: 10/10/2014 20:06:00, Event start: 2014:10:11:7:00:00, Event end: 2014:10:11:7:00:00","Cod:":"NetTestNoInflowsRain_2014:10:09:15:13:28_n03"},"crs":null,"bbox":null},{"id":"214","geometry":{"coordinates":{"longitude":-6.00089057549268,"altitude":"NaN","latitude":37.3735279458035},"properties":{},"crs":null,"bbox":null},"properties":{"Desc:":"Node:pb05, Alarm Type: ALARMA 2, Flood Depth:0,42, Time Max. Flood: 10/10/2014 20:07:00, Event start: 2014:10:11:7:00:00, Event end: 2014:10:11:7:00:00","Cod:":"NetTestNoInflowsRain_2014:10:09:15:13:28_pb05"},"crs":null,"bbox":null},{"id":"215","geometry":{"coordinates":{"longitude":-6.00171405340609,"altitude":"NaN","latitude":37.3745841191212},"properties":{},"crs":null,"bbox":null},"properties":{"Desc:":"Node:Nuevo2, Alarm Type: ALARMA 1, Flood Depth:0,123, Time Max. Flood: 10/10/2014 20:05:00, Event start: 2014:10:11:7:00:00, Event end: 2014:10:11:7:00:00","Cod:":"NetTestNoInflowsRain_2014:10:09:15:13:28_Nuevo2"},"crs":null,"bbox":null},{"id":"216","geometry":{"coordinates":{"longitude":-5.99520092079263,"altitude":"NaN","latitude":37.3753827747689},"properties":{},"crs":null,"bbox":null},"properties":{"Desc:":"Discharge:WR-01, Alarm Type: ALARMA 3, Total volume:629733,6, Critical Point: CPO-01, Event start: 2014:10:10:20:00:00, Event end: 2014:10:11:7:00:00","Cod:":"NetTestNoInflowsRain_2014:10:09:15:13:28_WR-01"},"crs":null,"bbox":null},{"id":"217","geometry":{"coordinates":{"longitude":-5.99329690170765,"altitude":"NaN","latitude":37.3756603322934},"properties":{},"crs":null,"bbox":null},"properties":{"Desc:":"Critical Point:CPO-01, Alarm Type: ALARMA 2, Max. Flow:135,355","Cod:":"NetTestNoInflowsRain_2014:10:09:15:13:28_CPO-01"},"crs":null,"bbox":null},{"id":"218","geometry":{"coordinates":{"longitude":-6.00241328412881,"altitude":"NaN","latitude":37.3734828468476},"properties":{},"crs":null,"bbox":null},"properties":{"Desc:":"Node:pb01, Alarm Type: ALARMA 1, Flood Depth:0, Time Max. Flood: 10/10/2014 20:04:00, Event start: , Event end: ","Cod:":"NetTestNoInflowsRain_2014:10:09:15:15:57_pb01"},"crs":null,"bbox":null},{"id":"219","geometry":{"coordinates":{"longitude":-6.0009243057943,"altitude":"NaN","latitude":37.3743323003151},"properties":{},"crs":null,"bbox":null},"properties":{"Desc:":"Node:n03, Alarm Type: ALARMA 1, Flood Depth:0, Time Max. Flood: 10/10/2014 20:07:00, Event start: , Event end: ","Cod:":"NetTestNoInflowsRain_2014:10:09:15:15:57_n03"},"crs":null,"bbox":null},{"id":"220","geometry":{"coordinates":{"longitude":-6.00089057549268,"altitude":"NaN","latitude":37.3735279458035},"properties":{},"crs":null,"bbox":null},"properties":{"Desc:":"Node:pb05, Alarm Type: ALARMA 1, Flood Depth:0, Time Max. Flood: 10/10/2014 20:04:00, Event start: , Event end: ","Cod:":"NetTestNoInflowsRain_2014:10:09:15:15:57_pb05"},"crs":null,"bbox":null},{"id":"221","geometry":{"coordinates":{"longitude":-6.00171405340609,"altitude":"NaN","latitude":37.3745841191212},"properties":{},"crs":null,"bbox":null},"properties":{"Desc:":"Node:Nuevo2, Alarm Type: ALARMA 1, Flood Depth:0,003, Time Max. Flood: 10/10/2014 20:07:00, Event start: , Event end: ","Cod:":"NetTestNoInflowsRain_2014:10:09:15:15:57_Nuevo2"},"crs":null,"bbox":null},{"id":"222","geometry":{"coordinates":{"longitude":-5.99520092079263,"altitude":"NaN","latitude":37.3753827747689},"properties":{},"crs":null,"bbox":null},"properties":{"Desc:":"Discharge:WR-01, Alarm Type: ALARMA 3, Total volume:466185,6, Critical Point: CPO-01, Event start: 2014:10:11:7:00:00, Event end: 2014:10:11:7:00:00","Cod:":"NetTestNoInflowsRain_2014:10:09:15:15:57_WR-01"},"crs":null,"bbox":null},{"id":"223","geometry":{"coordinates":{"longitude":-5.99329690170765,"altitude":"NaN","latitude":37.3756603322934},"properties":{},"crs":null,"bbox":null},"properties":{"Desc:":"Critical Point:CPO-01, Alarm Type: ALARMA 2, Max. Flow:129,496","Cod:":"NetTestNoInflowsRain_2014:10:09:15:15:57_CPO-01"},"crs":null,"bbox":null}],"properties":{},"crs":null,"bbox":null}



